creme/__init__.py
creme/creme.py
creme/custom_model.py
creme/shuffle.py
creme/utils.py
creme_nn-0.2.5.dist-info/LICENSE
creme_nn-0.2.5.dist-info/METADATA
creme_nn-0.2.5.dist-info/WHEEL
creme_nn-0.2.5.dist-info/top_level.txt
creme_nn-0.2.5.dist-info/RECORD
